torchnd/__init__.py
torchnd/functional.py
torchnd/modules.py
torchnd-0.1.0.dist-info/METADATA
torchnd-0.1.0.dist-info/WHEEL
torchnd-0.1.0.dist-info/top_level.txt
torchnd-0.1.0.dist-info/RECORD
