Metadata-Version: 2.4
Name: torchnd
Version: 0.1.0
Summary: ND Convolution for PyTorch
Author-email: Felix Zimmermann <fzimmermann89@gmail.com>
License: GPL-3.0-or-later
Project-URL: Homepage, https://github.com/fzimmermann89/torch_conv_nd
Project-URL: Repository, https://github.com/fzimmermann89/torch_conv_nd
Project-URL: Issues, https://github.com/fzimmermann89/torch_conv_nd/issues
Classifier: Development Status :: 3 - Alpha
Classifier: Intended Audience :: Developers
Classifier: Intended Audience :: Science/Research
Classifier: License :: OSI Approved :: GNU General Public License v3 or later (GPLv3+)
Classifier: Programming Language :: Python :: 3
Classifier: Programming Language :: Python :: 3.10
Classifier: Programming Language :: Python :: 3.11
Classifier: Programming Language :: Python :: 3.12
Classifier: Programming Language :: Python :: 3.13
Classifier: Topic :: Scientific/Engineering :: Artificial Intelligence
Requires-Python: >=3.10
Requires-Dist: torch>=2.0.0
Requires-Dist: einops>=0.6.0
Provides-Extra: dev
Requires-Dist: pytest>=7.4.0; extra == "dev"
Requires-Dist: pytest-cov>=4.1.0; extra == "dev"
Requires-Dist: ruff>=0.1.0; extra == "dev"
Requires-Dist: mypy>=1.5.0; extra == "dev"
Requires-Dist: pre-commit>=3.4.0; extra == "dev"
Requires-Dist: types-setuptools; extra == "dev"
